pyphasefield/__init__.py
pyphasefield/__main__.py
pyphasefield/field.py
pyphasefield/jit_placeholder.py
pyphasefield/parallel_utils.py
pyphasefield/ppf_gpu_utils.py
pyphasefield/ppf_utils.py
pyphasefield/simulation.py
pyphasefield/simulation_hdf.py
pyphasefield/test_python_script.py
pyphasefield/test_script.py
pyphasefield/test_script2.py
pyphasefield/test_script3.py
pyphasefield/Engines/AnisoDorrGPU.py
pyphasefield/Engines/CahnAllen.py
pyphasefield/Engines/CahnHilliard.py
pyphasefield/Engines/Diffusion.py
pyphasefield/Engines/Karma2001.py
pyphasefield/Engines/KarmaRappel1996.py
pyphasefield/Engines/KarmaRappel1998.py
pyphasefield/Engines/NCGPU.py
pyphasefield/Engines/NCGPU_new.py
pyphasefield/Engines/NComponent.py
pyphasefield/Engines/Template.py
pyphasefield/Engines/Warren1995.py
pyphasefield/Engines/__init__.py
pyphasefield/tests/__init__.py
pyphasefield/tests/test_Diffusion.py
pyphasefield/tests/test_NComponent.py
pyphasefield/tests/test_SaveLoad.py
pyphasefield/tests/test_Warren1995.py
pyphasefield/tests/test_boundary_conditions_validation.py
pyphasefield-3.0.3.dist-info/licenses/LICENSE
pyphasefield-3.0.3.dist-info/METADATA
pyphasefield-3.0.3.dist-info/WHEEL
pyphasefield-3.0.3.dist-info/top_level.txt
pyphasefield-3.0.3.dist-info/RECORD
