Metadata-Version: 2.4
Name: pyphasefield
Version: 3.0.3
Summary: Python phase field simulation
Home-page: https://github.com/AdditiveModeling/pyphasefield
Author: Scott Peters
Author-email: scott@dpeters.net
Classifier: Programming Language :: Python :: 3
Classifier: License :: OSI Approved :: MIT License
Classifier: Operating System :: OS Independent
Requires-Python: >=3.10
License-File: LICENSE
Requires-Dist: numpy<2.0,>=1.13
Requires-Dist: pycalphad>=0.11
Requires-Dist: sympy>=1.12
Dynamic: author
Dynamic: author-email
Dynamic: classifier
Dynamic: description
Dynamic: description-content-type
Dynamic: home-page
Dynamic: license-file
Dynamic: requires-dist
Dynamic: requires-python
Dynamic: summary
